keieru/__init__.py
keieru/courses.py
keieru/utils.py
keieru-0.1.0.dist-info/METADATA
keieru-0.1.0.dist-info/WHEEL
keieru-0.1.0.dist-info/top_level.txt
keieru-0.1.0.dist-info/RECORD
